[
    {
        "_id": "{{@ system @}}-{{@ datatype @}}-collect",
        "add_namespaces": false,
        "metadata": {},
        "source": {
            "id_expression": "{{ id }}",
            "operation": "get",
            "payload_property": "data",
            "properties": {
                "fields": "Account_Name,Amount,Campaign_Source,Closing_Date,Contact_Name,Created_By,Created_Time,Deal_Name,Description,Expected_Revenue,Last_Activity_Time,Lead_Conversion_Time,Lead_Source,Modified_By,Modified_Time,Next_Step,Overall_Sales_Duration,Owner,Probability,Sales_Cycle_Duration,Stage,Type",
                "module": "Deals"
            },
            "system": "{{@ system @}}",
            "type": "rest"
        },
        "type": "pipe"
    },
    {
        "_id": "{{@ system @}}-{{@ datatype @}}-share",
        "metadata": {},
        "sink": {
            "operation": "upsert",
            "properties": {
                "module": "Deals"
            },
            "system": "{{@ system @}}",
            "type": "rest"
        },
        "source": {
            "dataset": "{{@ system @}}-{{@ datatype @}}-transform",
            "type": "dataset"
        },
        "type": "pipe"
    }
]